banelib/__init__.py
banelib/bruteforcer.py
banelib/ddos.py
banelib/extrafun.py
banelib/filt.py
banelib/hasher.py
banelib/infos.py
banelib/iot.py
banelib/pager.py
banelib/payloads.py
banelib/proxer.py
banelib/vulns.py
banelib/wp.py
banelib-1.9.5.dist-info/LICENSE
banelib-1.9.5.dist-info/METADATA
banelib-1.9.5.dist-info/WHEEL
banelib-1.9.5.dist-info/top_level.txt
banelib-1.9.5.dist-info/RECORD
