Metadata-Version: 2.1
Name: banelib
Version: 1.9.5
Summary: cyber security library
Home-page: https://github.com/AlaBouali/bane
Author: AlaBouali
Author-email: trap.leader.123@gmail.com
License: MIT License
Platform: UNKNOWN
Classifier: Programming Language :: Python
Classifier: License :: OSI Approved :: MIT License 
Requires-Python: >=2.7
Requires-Dist: requests
Requires-Dist: PySocks
Requires-Dist: bs4
Requires-Dist: pexpect
Requires-Dist: paramiko
Requires-Dist: mysql-connector
Requires-Dist: kamene
Requires-Dist: stem
Requires-Dist: cfscrape
